odoo/addons/vertical_carsharing/__init__.py
odoo/addons/vertical_carsharing/__manifest__.py
odoo/addons/vertical_carsharing/email_tmpl/notification_email.xml
odoo/addons/vertical_carsharing/models/__init__.py
odoo/addons/vertical_carsharing/models/models_sm_company.py
odoo/addons/vertical_carsharing/models/models_sm_member.py
odoo/addons/vertical_carsharing/models/models_sm_res_config_settings.py
odoo/addons/vertical_carsharing/static/src/img/carsharing.png
odoo/addons/vertical_carsharing/static/src/less/variables.less
odoo/addons/vertical_carsharing/views/views.xml
odoo/addons/vertical_carsharing/views/views_members.xml
odoo/addons/vertical_carsharing/views/views_res_config_settings.xml
odoo11_addon_vertical_carsharing-11.0.0.0.2.dist-info/METADATA
odoo11_addon_vertical_carsharing-11.0.0.0.2.dist-info/WHEEL
odoo11_addon_vertical_carsharing-11.0.0.0.2.dist-info/top_level.txt
odoo11_addon_vertical_carsharing-11.0.0.0.2.dist-info/RECORD
